README
py2pdf.py
setup.py
py2pdf.egg-info/PKG-INFO
py2pdf.egg-info/SOURCES.txt
py2pdf.egg-info/dependency_links.txt
py2pdf.egg-info/top_level.txt