Metadata-Version: 1.2
Name: py2pdf
Version: 0.1.2
Summary: Python source to pdf conversion library.
Home-page: https://github.com/chrisecker/py2pdf
Author: C. Ecker
Author-email: textmodelview@gmail.com
License: BSD
Platform: any
Requires-Python: <3.0
